{
  "05981": {
    "sections": {
      "001": {
        "sentence_ids": [
          "001-01",
          "001-02",
          "001-03",
          "001-04",
          "001-05",
          "001-06",
          "001-07"
        ]
      },
      "002": {
        "sentence_ids": [
          "002-01",
          "002-02",
          "002-03",
          "002-04",
          "002-05",
          "002-06",
          "002-07",
          "002-08",
          "002-09",
          "002-10",
          "002-11",
          "002-12",
          "002-13",
          "002-14"
        ]
      },
      "003": {
        "sentence_ids": [
          "003-01",
          "003-02",
          "003-03",
          "003-04",
          "003-05",
          "003-06",
          "003-07"
        ]
      },
      "004": {
        "sentence_ids": [
          "004-01",
          "004-02",
          "004-03",
          "004-04",
          "004-05",
          "004-06"
        ]
      },
      "005": {
        "sentence_ids": [
          "005-01",
          "005-02",
          "005-03",
          "005-04",
          "005-05"
        ]
      },
      "006": {
        "sentence_ids": [
          "006-01",
          "006-02",
          "006-03",
          "006-04",
          "006-05",
          "006-06",
          "006-07",
          "006-08",
          "006-09",
          "006-10",
          "006-11"
        ]
      },
      "007": {
        "sentence_ids": [
          "007-01",
          "007-02",
          "007-03",
          "007-04",
          "007-05",
          "007-06",
          "007-07",
          "007-08",
          "007-09",
          "007-10",
          "007-11"
        ]
      },
      "008": {
        "sentence_ids": [
          "008-01",
          "008-02",
          "008-03",
          "008-04",
          "008-05",
          "008-06",
          "008-07"
        ]
      },
      "009": {
        "sentence_ids": [
          "009-01",
          "009-02",
          "009-03",
          "009-04",
          "009-05",
          "009-06",
          "009-07"
        ]
      },
      "010": {
        "sentence_ids": [
          "010-01",
          "010-02",
          "010-03",
          "010-04",
          "010-05",
          "010-06",
          "010-07"
        ]
      },
      "011": {
        "sentence_ids": [
          "011-01",
          "011-02",
          "011-03",
          "011-04",
          "011-05",
          "011-06",
          "011-07",
          "011-08",
          "011-09",
          "011-10",
          "011-11",
          "011-12",
          "011-13"
        ]
      },
      "012": {
        "sentence_ids": [
          "012-01",
          "012-02",
          "012-03",
          "012-04",
          "012-05",
          "012-06",
          "012-07",
          "012-08",
          "012-09",
          "012-10"
        ]
      },
      "013": {
        "sentence_ids": [
          "013-01",
          "013-02",
          "013-03",
          "013-04",
          "013-05",
          "013-06",
          "013-07",
          "013-08"
        ]
      }
    },
    "sentences": {
      "001-01": {
        "section_id": "001",
        "span_in_orig_text": [
          0,
          44
        ],
        "text": "",
        "mention_ids": [
          "M018",
          "M019",
          "M047",
          "M048"
        ]
      },
      "001-02": {
        "section_id": "001",
        "span_in_orig_text": [
          44,
          62
        ],
        "text": "",
        "mention_ids": []
      },
      "001-03": {
        "section_id": "001",
        "span_in_orig_text": [
          62,
          89
        ],
        "text": "",
        "mention_ids": [
          "M020",
          "M021"
        ]
      },
      "001-04": {
        "section_id": "001",
        "span_in_orig_text": [
          89,
          105
        ],
        "text": "",
        "mention_ids": []
      },
      "001-05": {
        "section_id": "001",
        "span_in_orig_text": [
          105,
          127
        ],
        "text": "",
        "mention_ids": [
          "M001"
        ]
      },
      "001-06": {
        "section_id": "001",
        "span_in_orig_text": [
          127,
          143
        ],
        "text": "",
        "mention_ids": []
      },
      "001-07": {
        "section_id": "001",
        "span_in_orig_text": [
          143,
          163
        ],
        "text": "",
        "mention_ids": []
      },
      "002-01": {
        "section_id": "002",
        "span_in_orig_text": [
          0,
          49
        ],
        "text": "",
        "mention_ids": [
          "M002",
          "M004",
          "M050"
        ]
      },
      "002-02": {
        "section_id": "002",
        "span_in_orig_text": [
          49,
          70
        ],
        "text": "",
        "mention_ids": []
      },
      "002-03": {
        "section_id": "002",
        "span_in_orig_text": [
          70,
          77
        ],
        "text": "",
        "mention_ids": []
      },
      "002-04": {
        "section_id": "002",
        "span_in_orig_text": [
          77,
          99
        ],
        "text": "",
        "mention_ids": []
      },
      "002-05": {
        "section_id": "002",
        "span_in_orig_text": [
          99,
          127
        ],
        "text": "",
        "mention_ids": []
      },
      "002-06": {
        "section_id": "002",
        "span_in_orig_text": [
          127,
          146
        ],
        "text": "",
        "mention_ids": []
      },
      "002-07": {
        "section_id": "002",
        "span_in_orig_text": [
          146,
          168
        ],
        "text": "",
        "mention_ids": []
      },
      "002-08": {
        "section_id": "002",
        "span_in_orig_text": [
          168,
          187
        ],
        "text": "",
        "mention_ids": []
      },
      "002-09": {
        "section_id": "002",
        "span_in_orig_text": [
          187,
          202
        ],
        "text": "",
        "mention_ids": []
      },
      "002-10": {
        "section_id": "002",
        "span_in_orig_text": [
          202,
          215
        ],
        "text": "",
        "mention_ids": []
      },
      "002-11": {
        "section_id": "002",
        "span_in_orig_text": [
          215,
          228
        ],
        "text": "",
        "mention_ids": []
      },
      "002-12": {
        "section_id": "002",
        "span_in_orig_text": [
          228,
          236
        ],
        "text": "",
        "mention_ids": []
      },
      "002-13": {
        "section_id": "002",
        "span_in_orig_text": [
          236,
          256
        ],
        "text": "",
        "mention_ids": []
      },
      "002-14": {
        "section_id": "002",
        "span_in_orig_text": [
          256,
          280
        ],
        "text": "",
        "mention_ids": []
      },
      "003-01": {
        "section_id": "003",
        "span_in_orig_text": [
          0,
          17
        ],
        "text": "",
        "mention_ids": [
          "M003",
          "M005"
        ]
      },
      "003-02": {
        "section_id": "003",
        "span_in_orig_text": [
          17,
          51
        ],
        "text": "",
        "mention_ids": [
          "M022",
          "M023"
        ]
      },
      "003-03": {
        "section_id": "003",
        "span_in_orig_text": [
          51,
          97
        ],
        "text": "",
        "mention_ids": [
          "M006",
          "M024",
          "M051"
        ]
      },
      "003-04": {
        "section_id": "003",
        "span_in_orig_text": [
          97,
          128
        ],
        "text": "",
        "mention_ids": [
          "M007",
          "M025"
        ]
      },
      "003-05": {
        "section_id": "003",
        "span_in_orig_text": [
          128,
          162
        ],
        "text": "",
        "mention_ids": []
      },
      "003-06": {
        "section_id": "003",
        "span_in_orig_text": [
          162,
          181
        ],
        "text": "",
        "mention_ids": []
      },
      "003-07": {
        "section_id": "003",
        "span_in_orig_text": [
          181,
          205
        ],
        "text": "",
        "mention_ids": []
      },
      "004-01": {
        "section_id": "004",
        "span_in_orig_text": [
          0,
          14
        ],
        "text": "",
        "mention_ids": [
          "M052"
        ]
      },
      "004-02": {
        "section_id": "004",
        "span_in_orig_text": [
          14,
          27
        ],
        "text": "",
        "mention_ids": [
          "M008"
        ]
      },
      "004-03": {
        "section_id": "004",
        "span_in_orig_text": [
          27,
          81
        ],
        "text": "",
        "mention_ids": [
          "M009",
          "M010",
          "M053"
        ]
      },
      "004-04": {
        "section_id": "004",
        "span_in_orig_text": [
          81,
          88
        ],
        "text": "",
        "mention_ids": [
          "M011"
        ]
      },
      "004-05": {
        "section_id": "004",
        "span_in_orig_text": [
          88,
          144
        ],
        "text": "",
        "mention_ids": [
          "M026",
          "M027"
        ]
      },
      "004-06": {
        "section_id": "004",
        "span_in_orig_text": [
          144,
          160
        ],
        "text": "",
        "mention_ids": []
      },
      "005-01": {
        "section_id": "005",
        "span_in_orig_text": [
          0,
          11
        ],
        "text": "",
        "mention_ids": [
          "M012"
        ]
      },
      "005-02": {
        "section_id": "005",
        "span_in_orig_text": [
          11,
          32
        ],
        "text": "",
        "mention_ids": []
      },
      "005-03": {
        "section_id": "005",
        "span_in_orig_text": [
          32,
          112
        ],
        "text": "",
        "mention_ids": []
      },
      "005-04": {
        "section_id": "005",
        "span_in_orig_text": [
          112,
          135
        ],
        "text": "",
        "mention_ids": []
      },
      "005-05": {
        "section_id": "005",
        "span_in_orig_text": [
          135,
          161
        ],
        "text": "",
        "mention_ids": []
      },
      "006-01": {
        "section_id": "006",
        "span_in_orig_text": [
          0,
          18
        ],
        "text": "",
        "mention_ids": []
      },
      "006-02": {
        "section_id": "006",
        "span_in_orig_text": [
          18,
          49
        ],
        "text": "",
        "mention_ids": []
      },
      "006-03": {
        "section_id": "006",
        "span_in_orig_text": [
          49,
          78
        ],
        "text": "",
        "mention_ids": []
      },
      "006-04": {
        "section_id": "006",
        "span_in_orig_text": [
          78,
          99
        ],
        "text": "",
        "mention_ids": []
      },
      "006-05": {
        "section_id": "006",
        "span_in_orig_text": [
          99,
          117
        ],
        "text": "",
        "mention_ids": []
      },
      "006-06": {
        "section_id": "006",
        "span_in_orig_text": [
          117,
          136
        ],
        "text": "",
        "mention_ids": [
          "M028"
        ]
      },
      "006-07": {
        "section_id": "006",
        "span_in_orig_text": [
          136,
          147
        ],
        "text": "",
        "mention_ids": []
      },
      "006-08": {
        "section_id": "006",
        "span_in_orig_text": [
          147,
          167
        ],
        "text": "",
        "mention_ids": []
      },
      "006-09": {
        "section_id": "006",
        "span_in_orig_text": [
          167,
          186
        ],
        "text": "",
        "mention_ids": []
      },
      "006-10": {
        "section_id": "006",
        "span_in_orig_text": [
          186,
          189
        ],
        "text": "",
        "mention_ids": []
      },
      "006-11": {
        "section_id": "006",
        "span_in_orig_text": [
          189,
          193
        ],
        "text": "",
        "mention_ids": [
          "M056"
        ]
      },
      "007-01": {
        "section_id": "007",
        "span_in_orig_text": [
          0,
          44
        ],
        "text": "",
        "mention_ids": [
          "M013",
          "M029"
        ]
      },
      "007-02": {
        "section_id": "007",
        "span_in_orig_text": [
          44,
          62
        ],
        "text": "",
        "mention_ids": [
          "M014",
          "M058"
        ]
      },
      "007-03": {
        "section_id": "007",
        "span_in_orig_text": [
          62,
          98
        ],
        "text": "",
        "mention_ids": [
          "M030",
          "M054"
        ]
      },
      "007-04": {
        "section_id": "007",
        "span_in_orig_text": [
          98,
          117
        ],
        "text": "",
        "mention_ids": []
      },
      "007-05": {
        "section_id": "007",
        "span_in_orig_text": [
          117,
          141
        ],
        "text": "",
        "mention_ids": []
      },
      "007-06": {
        "section_id": "007",
        "span_in_orig_text": [
          141,
          163
        ],
        "text": "",
        "mention_ids": []
      },
      "007-07": {
        "section_id": "007",
        "span_in_orig_text": [
          163,
          182
        ],
        "text": "",
        "mention_ids": []
      },
      "007-08": {
        "section_id": "007",
        "span_in_orig_text": [
          182,
          205
        ],
        "text": "",
        "mention_ids": [
          "M031"
        ]
      },
      "007-09": {
        "section_id": "007",
        "span_in_orig_text": [
          205,
          227
        ],
        "text": "",
        "mention_ids": []
      },
      "007-10": {
        "section_id": "007",
        "span_in_orig_text": [
          227,
          240
        ],
        "text": "",
        "mention_ids": []
      },
      "007-11": {
        "section_id": "007",
        "span_in_orig_text": [
          240,
          251
        ],
        "text": "",
        "mention_ids": []
      },
      "008-01": {
        "section_id": "008",
        "span_in_orig_text": [
          0,
          15
        ],
        "text": "",
        "mention_ids": [
          "M032"
        ]
      },
      "008-02": {
        "section_id": "008",
        "span_in_orig_text": [
          15,
          28
        ],
        "text": "",
        "mention_ids": [
          "M033"
        ]
      },
      "008-03": {
        "section_id": "008",
        "span_in_orig_text": [
          28,
          61
        ],
        "text": "",
        "mention_ids": [
          "M034"
        ]
      },
      "008-04": {
        "section_id": "008",
        "span_in_orig_text": [
          61,
          72
        ],
        "text": "",
        "mention_ids": []
      },
      "008-05": {
        "section_id": "008",
        "span_in_orig_text": [
          72,
          94
        ],
        "text": "",
        "mention_ids": [
          "M035"
        ]
      },
      "008-06": {
        "section_id": "008",
        "span_in_orig_text": [
          94,
          111
        ],
        "text": "",
        "mention_ids": [
          "M045"
        ]
      },
      "008-07": {
        "section_id": "008",
        "span_in_orig_text": [
          111,
          127
        ],
        "text": "",
        "mention_ids": []
      },
      "009-01": {
        "section_id": "009",
        "span_in_orig_text": [
          0,
          14
        ],
        "text": "",
        "mention_ids": [
          "M036"
        ]
      },
      "009-02": {
        "section_id": "009",
        "span_in_orig_text": [
          14,
          32
        ],
        "text": "",
        "mention_ids": []
      },
      "009-03": {
        "section_id": "009",
        "span_in_orig_text": [
          32,
          62
        ],
        "text": "",
        "mention_ids": []
      },
      "009-04": {
        "section_id": "009",
        "span_in_orig_text": [
          62,
          79
        ],
        "text": "",
        "mention_ids": []
      },
      "009-05": {
        "section_id": "009",
        "span_in_orig_text": [
          79,
          112
        ],
        "text": "",
        "mention_ids": [
          "M037"
        ]
      },
      "009-06": {
        "section_id": "009",
        "span_in_orig_text": [
          112,
          157
        ],
        "text": "",
        "mention_ids": [
          "M038"
        ]
      },
      "009-07": {
        "section_id": "009",
        "span_in_orig_text": [
          157,
          172
        ],
        "text": "",
        "mention_ids": []
      },
      "010-01": {
        "section_id": "010",
        "span_in_orig_text": [
          0,
          21
        ],
        "text": "",
        "mention_ids": [
          "M039"
        ]
      },
      "010-02": {
        "section_id": "010",
        "span_in_orig_text": [
          21,
          59
        ],
        "text": "",
        "mention_ids": [
          "M040"
        ]
      },
      "010-03": {
        "section_id": "010",
        "span_in_orig_text": [
          59,
          74
        ],
        "text": "",
        "mention_ids": [
          "M041"
        ]
      },
      "010-04": {
        "section_id": "010",
        "span_in_orig_text": [
          74,
          127
        ],
        "text": "",
        "mention_ids": []
      },
      "010-05": {
        "section_id": "010",
        "span_in_orig_text": [
          127,
          167
        ],
        "text": "",
        "mention_ids": []
      },
      "010-06": {
        "section_id": "010",
        "span_in_orig_text": [
          167,
          182
        ],
        "text": "",
        "mention_ids": [
          "M015"
        ]
      },
      "010-07": {
        "section_id": "010",
        "span_in_orig_text": [
          182,
          196
        ],
        "text": "",
        "mention_ids": []
      },
      "011-01": {
        "section_id": "011",
        "span_in_orig_text": [
          0,
          14
        ],
        "text": "",
        "mention_ids": [
          "M016"
        ]
      },
      "011-02": {
        "section_id": "011",
        "span_in_orig_text": [
          14,
          27
        ],
        "text": "",
        "mention_ids": []
      },
      "011-03": {
        "section_id": "011",
        "span_in_orig_text": [
          27,
          42
        ],
        "text": "",
        "mention_ids": []
      },
      "011-04": {
        "section_id": "011",
        "span_in_orig_text": [
          42,
          63
        ],
        "text": "",
        "mention_ids": []
      },
      "011-05": {
        "section_id": "011",
        "span_in_orig_text": [
          63,
          87
        ],
        "text": "",
        "mention_ids": []
      },
      "011-06": {
        "section_id": "011",
        "span_in_orig_text": [
          87,
          117
        ],
        "text": "",
        "mention_ids": []
      },
      "011-07": {
        "section_id": "011",
        "span_in_orig_text": [
          117,
          151
        ],
        "text": "",
        "mention_ids": []
      },
      "011-08": {
        "section_id": "011",
        "span_in_orig_text": [
          151,
          168
        ],
        "text": "",
        "mention_ids": []
      },
      "011-09": {
        "section_id": "011",
        "span_in_orig_text": [
          168,
          191
        ],
        "text": "",
        "mention_ids": []
      },
      "011-10": {
        "section_id": "011",
        "span_in_orig_text": [
          191,
          210
        ],
        "text": "",
        "mention_ids": []
      },
      "011-11": {
        "section_id": "011",
        "span_in_orig_text": [
          210,
          242
        ],
        "text": "",
        "mention_ids": []
      },
      "011-12": {
        "section_id": "011",
        "span_in_orig_text": [
          242,
          262
        ],
        "text": "",
        "mention_ids": []
      },
      "011-13": {
        "section_id": "011",
        "span_in_orig_text": [
          262,
          276
        ],
        "text": "",
        "mention_ids": []
      },
      "012-01": {
        "section_id": "012",
        "span_in_orig_text": [
          0,
          29
        ],
        "text": "",
        "mention_ids": []
      },
      "012-02": {
        "section_id": "012",
        "span_in_orig_text": [
          29,
          42
        ],
        "text": "",
        "mention_ids": [
          "M057"
        ]
      },
      "012-03": {
        "section_id": "012",
        "span_in_orig_text": [
          42,
          61
        ],
        "text": "",
        "mention_ids": []
      },
      "012-04": {
        "section_id": "012",
        "span_in_orig_text": [
          61,
          87
        ],
        "text": "",
        "mention_ids": []
      },
      "012-05": {
        "section_id": "012",
        "span_in_orig_text": [
          87,
          106
        ],
        "text": "",
        "mention_ids": []
      },
      "012-06": {
        "section_id": "012",
        "span_in_orig_text": [
          106,
          119
        ],
        "text": "",
        "mention_ids": []
      },
      "012-07": {
        "section_id": "012",
        "span_in_orig_text": [
          119,
          138
        ],
        "text": "",
        "mention_ids": []
      },
      "012-08": {
        "section_id": "012",
        "span_in_orig_text": [
          138,
          155
        ],
        "text": "",
        "mention_ids": []
      },
      "012-09": {
        "section_id": "012",
        "span_in_orig_text": [
          155,
          172
        ],
        "text": "",
        "mention_ids": []
      },
      "012-10": {
        "section_id": "012",
        "span_in_orig_text": [
          172,
          199
        ],
        "text": "",
        "mention_ids": []
      },
      "013-01": {
        "section_id": "013",
        "span_in_orig_text": [
          0,
          28
        ],
        "text": "",
        "mention_ids": [
          "M055"
        ]
      },
      "013-02": {
        "section_id": "013",
        "span_in_orig_text": [
          28,
          44
        ],
        "text": "",
        "mention_ids": []
      },
      "013-03": {
        "section_id": "013",
        "span_in_orig_text": [
          44,
          65
        ],
        "text": "",
        "mention_ids": []
      },
      "013-04": {
        "section_id": "013",
        "span_in_orig_text": [
          65,
          91
        ],
        "text": "",
        "mention_ids": [
          "M042",
          "M043",
          "M049"
        ]
      },
      "013-05": {
        "section_id": "013",
        "span_in_orig_text": [
          91,
          96
        ],
        "text": "",
        "mention_ids": []
      },
      "013-06": {
        "section_id": "013",
        "span_in_orig_text": [
          96,
          129
        ],
        "text": "",
        "mention_ids": [
          "M044"
        ]
      },
      "013-07": {
        "section_id": "013",
        "span_in_orig_text": [
          129,
          143
        ],
        "text": "",
        "mention_ids": [
          "M017",
          "M046"
        ]
      },
      "013-08": {
        "section_id": "013",
        "span_in_orig_text": [
          143,
          154
        ],
        "text": "",
        "mention_ids": []
      }
    },
    "mentions": {
      "M018": {
        "sentence_id": "001-01",
        "entity_id": null,
        "span": [
          0,
          2
        ],
        "text": "",
        "entity_type": "FAC_NOM",
        "generic": true
      },
      "M047": {
        "sentence_id": "001-01",
        "entity_id": null,
        "span": [
          6,
          8
        ],
        "text": "",
        "entity_type": "LOC_NOM",
        "generic": true
      },
      "M019": {
        "sentence_id": "001-01",
        "entity_id": "E001",
        "span": [
          24,
          26
        ],
        "text": "",
        "entity_type": "DEICTIC"
      },
      "M048": {
        "sentence_id": "001-01",
        "entity_id": null,
        "span": [
          27,
          28
        ],
        "text": "",
        "entity_type": "LOC_NOM",
        "ref_spec_amb": true
      },
      "M020": {
        "sentence_id": "001-03",
        "entity_id": "E002",
        "span": [
          2,
          4
        ],
        "text": "",
        "entity_type": "FAC_NOM"
      },
      "M021": {
        "sentence_id": "001-03",
        "entity_id": "E003",
        "span": [
          13,
          16
        ],
        "text": "",
        "entity_type": "FAC_NOM"
      },
      "M001": {
        "sentence_id": "001-05",
        "entity_id": "E004",
        "span": [
          6,
          15
        ],
        "text": "",
        "entity_type": "FAC_NAME"
      },
      "M002": {
        "sentence_id": "002-01",
        "entity_id": "E005",
        "span": [
          0,
          6
        ],
        "text": "",
        "entity_type": "FAC_NAME"
      },
      "M050": {
        "sentence_id": "002-01",
        "entity_id": "E006",
        "span": [
          24,
          26
        ],
        "text": "",
        "entity_type": "LOC_OR_FAC"
      },
      "M004": {
        "sentence_id": "002-01",
        "entity_id": "E007",
        "span": [
          28,
          32
        ],
        "text": "",
        "entity_type": "FAC_NAME"
      },
      "M005": {
        "sentence_id": "003-01",
        "entity_id": "E008",
        "span": [
          0,
          2
        ],
        "text": "",
        "entity_type": "LOC_NAME"
      },
      "M003": {
        "sentence_id": "003-01",
        "entity_id": null,
        "span": [
          7,
          10
        ],
        "text": "",
        "entity_type": "FAC_NOM",
        "generic": true
      },
      "M022": {
        "sentence_id": "003-02",
        "entity_id": "E005",
        "span": [
          2,
          5
        ],
        "text": "",
        "entity_type": "FAC_NOM"
      },
      "M023": {
        "sentence_id": "003-02",
        "entity_id": null,
        "span": [
          9,
          12
        ],
        "text": "",
        "entity_type": "FAC_NOM",
        "ref_spec_amb": true
      },
      "M006": {
        "sentence_id": "003-03",
        "entity_id": "E009",
        "span": [
          8,
          12
        ],
        "text": "",
        "entity_type": "FAC_NAME"
      },
      "M024": {
        "sentence_id": "003-03",
        "entity_id": "E010",
        "span": [
          20,
          29
        ],
        "text": "",
        "entity_type": "FAC_NAME"
      },
      "M051": {
        "sentence_id": "003-03",
        "entity_id": "E010",
        "span": [
          31,
          39
        ],
        "text": "",
        "entity_type": "FAC_NOM"
      },
      "M007": {
        "sentence_id": "003-04",
        "entity_id": "E009",
        "span": [
          0,
          4
        ],
        "text": "",
        "entity_type": "FAC_NAME"
      },
      "M025": {
        "sentence_id": "003-04",
        "entity_id": null,
        "span": [
          24,
          28
        ],
        "text": "",
        "entity_type": "FAC_NOM",
        "generic": true
      },
      "M052": {
        "sentence_id": "004-01",
        "entity_id": "E011",
        "span": [
          2,
          6
        ],
        "text": "",
        "entity_type": "LOC_OR_FAC"
      },
      "M008": {
        "sentence_id": "004-02",
        "entity_id": "E012",
        "span": [
          3,
          5
        ],
        "text": "",
        "entity_type": "LOC_NAME"
      },
      "M009": {
        "sentence_id": "004-03",
        "entity_id": "E013",
        "span": [
          3,
          5
        ],
        "text": "",
        "entity_type": "LOC_NAME"
      },
      "M010": {
        "sentence_id": "004-03",
        "entity_id": "E014",
        "span": [
          19,
          21
        ],
        "text": "",
        "entity_type": "LOC_NAME"
      },
      "M053": {
        "sentence_id": "004-03",
        "entity_id": "E015",
        "span": [
          39,
          46
        ],
        "text": "",
        "entity_type": "LINE_NOM"
      },
      "M011": {
        "sentence_id": "004-04",
        "entity_id": "E012",
        "span": [
          4,
          6
        ],
        "text": "",
        "entity_type": "LOC_NAME"
      },
      "M026": {
        "sentence_id": "004-05",
        "entity_id": "E016",
        "span": [
          7,
          9
        ],
        "text": "",
        "entity_type": "FAC_NOM"
      },
      "M027": {
        "sentence_id": "004-05",
        "entity_id": "E017",
        "span": [
          37,
          40
        ],
        "text": "",
        "entity_type": "FAC_NOM"
      },
      "M012": {
        "sentence_id": "005-01",
        "entity_id": "E018",
        "span": [
          0,
          3
        ],
        "text": "",
        "entity_type": "FAC_NAME"
      },
      "M028": {
        "sentence_id": "006-06",
        "entity_id": null,
        "span": [
          6,
          8
        ],
        "text": "",
        "entity_type": "FAC_NOM",
        "generic": true
      },
      "M056": {
        "sentence_id": "006-11",
        "entity_id": "E019",
        "span": [
          0,
          3
        ],
        "text": "",
        "entity_type": "LOC_NAME"
      },
      "M013": {
        "sentence_id": "007-01",
        "entity_id": "E020",
        "span": [
          3,
          6
        ],
        "text": "",
        "entity_type": "LOC_NAME"
      },
      "M029": {
        "sentence_id": "007-01",
        "entity_id": null,
        "span": [
          26,
          32
        ],
        "text": "",
        "entity_type": "TRANS_NOM"
      },
      "M058": {
        "sentence_id": "007-02",
        "entity_id": null,
        "span": [
          0,
          3
        ],
        "text": "",
        "entity_type": "DEICTIC",
        "generic": true
      },
      "M014": {
        "sentence_id": "007-02",
        "entity_id": "E021",
        "span": [
          4,
          7
        ],
        "text": "",
        "entity_type": "LOC_NAME"
      },
      "M054": {
        "sentence_id": "007-03",
        "entity_id": null,
        "span": [
          4,
          6
        ],
        "text": "",
        "entity_type": "LOC_NOM",
        "ref_spec_amb": true
      },
      "M030": {
        "sentence_id": "007-03",
        "entity_id": null,
        "span": [
          7,
          9
        ],
        "text": "",
        "entity_type": "TRANS_NOM"
      },
      "M031": {
        "sentence_id": "007-08",
        "entity_id": null,
        "span": [
          3,
          5
        ],
        "text": "",
        "entity_type": "FAC_NOM",
        "ref_spec_amb": true
      },
      "M032": {
        "sentence_id": "008-01",
        "entity_id": "E022",
        "span": [
          0,
          5
        ],
        "text": "",
        "entity_type": "FAC_NAME"
      },
      "M033": {
        "sentence_id": "008-02",
        "entity_id": "E023",
        "span": [
          3,
          4
        ],
        "text": "",
        "entity_type": "LINE_NOM"
      },
      "M034": {
        "sentence_id": "008-03",
        "entity_id": "E024",
        "span": [
          0,
          3
        ],
        "text": "",
        "entity_type": "FAC_NAME"
      },
      "M035": {
        "sentence_id": "008-05",
        "entity_id": "E022",
        "span": [
          0,
          5
        ],
        "text": "",
        "entity_type": "FAC_NAME"
      },
      "M045": {
        "sentence_id": "008-06",
        "entity_id": "E025",
        "span": [
          0,
          1
        ],
        "text": "",
        "entity_type": "FAC_NOM"
      },
      "M036": {
        "sentence_id": "009-01",
        "entity_id": "E024",
        "span": [
          0,
          3
        ],
        "text": "",
        "entity_type": "FAC_NAME"
      },
      "M037": {
        "sentence_id": "009-05",
        "entity_id": "E022",
        "span": [
          0,
          5
        ],
        "text": "",
        "entity_type": "FAC_NAME"
      },
      "M038": {
        "sentence_id": "009-06",
        "entity_id": "E026",
        "span": [
          9,
          11
        ],
        "text": "",
        "entity_type": "DEICTIC"
      },
      "M039": {
        "sentence_id": "010-01",
        "entity_id": "E024",
        "span": [
          5,
          8
        ],
        "text": "",
        "entity_type": "FAC_NAME"
      },
      "M040": {
        "sentence_id": "010-02",
        "entity_id": null,
        "span": [
          8,
          10
        ],
        "text": "",
        "entity_type": "FAC_NOM",
        "generic": true
      },
      "M041": {
        "sentence_id": "010-03",
        "entity_id": null,
        "span": [
          0,
          3
        ],
        "text": "",
        "entity_type": "FAC_NOM",
        "generic": true
      },
      "M015": {
        "sentence_id": "010-06",
        "entity_id": "E027",
        "span": [
          12,
          14
        ],
        "text": "",
        "entity_type": "FAC_NOM"
      },
      "M016": {
        "sentence_id": "011-01",
        "entity_id": "E028",
        "span": [
          0,
          2
        ],
        "text": "",
        "entity_type": "LOC_NAME"
      },
      "M057": {
        "sentence_id": "012-02",
        "entity_id": null,
        "span": [
          3,
          5
        ],
        "text": "",
        "entity_type": "LOC_NOM",
        "ref_spec_amb": true
      },
      "M055": {
        "sentence_id": "013-01",
        "entity_id": null,
        "span": [
          13,
          15
        ],
        "text": "",
        "entity_type": "LOC_NOM",
        "ref_spec_amb": true
      },
      "M049": {
        "sentence_id": "013-04",
        "entity_id": "E029",
        "span": [
          10,
          14
        ],
        "text": "",
        "entity_type": "FAC_NAME"
      },
      "M042": {
        "sentence_id": "013-04",
        "entity_id": "E030",
        "span": [
          15,
          18
        ],
        "text": "",
        "entity_type": "FAC_NOM"
      },
      "M043": {
        "sentence_id": "013-04",
        "entity_id": null,
        "span": [
          19,
          23
        ],
        "text": "",
        "entity_type": "TRANS_NOM"
      },
      "M044": {
        "sentence_id": "013-06",
        "entity_id": "E031",
        "span": [
          5,
          9
        ],
        "text": "",
        "entity_type": "LINE_NOM"
      },
      "M017": {
        "sentence_id": "013-07",
        "entity_id": "E032",
        "span": [
          2,
          6
        ],
        "text": "",
        "entity_type": "LOC_NAME"
      },
      "M046": {
        "sentence_id": "013-07",
        "entity_id": null,
        "span": [
          7,
          9
        ],
        "text": "",
        "entity_type": "FAC_NOM",
        "ref_spec_amb": true
      }
    },
    "entities": {
      "E001": {
        "original_entity_id": "C1",
        "entity_type_merged": "UNK",
        "has_name": false,
        "member_mention_ids": [
          "M019"
        ]
      },
      "E002": {
        "original_entity_id": "C2",
        "entity_type_merged": "FAC",
        "has_name": false,
        "member_mention_ids": [
          "M020"
        ]
      },
      "E003": {
        "original_entity_id": "C3",
        "entity_type_merged": "FAC",
        "has_name": false,
        "member_mention_ids": [
          "M021"
        ]
      },
      "E004": {
        "original_entity_id": "C4",
        "entity_type_merged": "FAC",
        "has_name": true,
        "member_mention_ids": [
          "M001"
        ]
      },
      "E005": {
        "original_entity_id": "C5",
        "entity_type_merged": "FAC",
        "has_name": true,
        "member_mention_ids": [
          "M002",
          "M022"
        ]
      },
      "E006": {
        "original_entity_id": "C6",
        "entity_type_merged": "UNK",
        "has_name": false,
        "member_mention_ids": [
          "M050"
        ]
      },
      "E007": {
        "original_entity_id": "C7",
        "entity_type_merged": "FAC",
        "has_name": true,
        "member_mention_ids": [
          "M004"
        ]
      },
      "E008": {
        "original_entity_id": "C8",
        "entity_type_merged": "LOC",
        "has_name": true,
        "member_mention_ids": [
          "M005"
        ]
      },
      "E009": {
        "original_entity_id": "C9",
        "entity_type_merged": "FAC",
        "has_name": true,
        "member_mention_ids": [
          "M006",
          "M007"
        ]
      },
      "E010": {
        "original_entity_id": "C10",
        "entity_type_merged": "FAC",
        "has_name": true,
        "coref_attr_pairs": "T24-T51",
        "member_mention_ids": [
          "M024",
          "M051"
        ]
      },
      "E011": {
        "original_entity_id": "C11",
        "entity_type_merged": "UNK",
        "has_name": false,
        "member_mention_ids": [
          "M052"
        ]
      },
      "E012": {
        "original_entity_id": "C12",
        "entity_type_merged": "LOC",
        "has_name": true,
        "member_mention_ids": [
          "M008",
          "M011"
        ]
      },
      "E013": {
        "original_entity_id": "C13",
        "entity_type_merged": "LOC",
        "has_name": true,
        "member_mention_ids": [
          "M009"
        ]
      },
      "E014": {
        "original_entity_id": "C14",
        "entity_type_merged": "LOC",
        "has_name": true,
        "member_mention_ids": [
          "M010"
        ]
      },
      "E015": {
        "original_entity_id": "C15",
        "entity_type_merged": "LINE",
        "has_name": false,
        "member_mention_ids": [
          "M053"
        ]
      },
      "E016": {
        "original_entity_id": "C16",
        "entity_type_merged": "FAC",
        "has_name": false,
        "member_mention_ids": [
          "M026"
        ]
      },
      "E017": {
        "original_entity_id": "C17",
        "entity_type_merged": "FAC",
        "has_name": false,
        "member_mention_ids": [
          "M027"
        ]
      },
      "E018": {
        "original_entity_id": "C18",
        "entity_type_merged": "FAC",
        "has_name": true,
        "member_mention_ids": [
          "M012"
        ]
      },
      "E019": {
        "original_entity_id": "C19",
        "entity_type_merged": "LOC",
        "has_name": true,
        "member_mention_ids": [
          "M056"
        ]
      },
      "E020": {
        "original_entity_id": "C20",
        "entity_type_merged": "LOC",
        "has_name": true,
        "member_mention_ids": [
          "M013"
        ]
      },
      "E021": {
        "original_entity_id": "C21",
        "entity_type_merged": "LOC",
        "has_name": true,
        "member_mention_ids": [
          "M014"
        ]
      },
      "E022": {
        "original_entity_id": "C22",
        "entity_type_merged": "FAC",
        "has_name": true,
        "member_mention_ids": [
          "M032",
          "M035",
          "M037"
        ]
      },
      "E023": {
        "original_entity_id": "C23",
        "entity_type_merged": "LINE",
        "has_name": false,
        "member_mention_ids": [
          "M033"
        ]
      },
      "E024": {
        "original_entity_id": "C24",
        "entity_type_merged": "FAC",
        "has_name": true,
        "member_mention_ids": [
          "M034",
          "M036",
          "M039"
        ]
      },
      "E025": {
        "original_entity_id": "C25",
        "entity_type_merged": "FAC",
        "has_name": false,
        "member_mention_ids": [
          "M045"
        ]
      },
      "E026": {
        "original_entity_id": "C26",
        "entity_type_merged": "UNK",
        "has_name": false,
        "member_mention_ids": [
          "M038"
        ]
      },
      "E027": {
        "original_entity_id": "C27",
        "entity_type_merged": "FAC",
        "has_name": false,
        "member_mention_ids": [
          "M015"
        ]
      },
      "E028": {
        "original_entity_id": "C28",
        "entity_type_merged": "LOC",
        "has_name": true,
        "member_mention_ids": [
          "M016"
        ]
      },
      "E029": {
        "original_entity_id": "C29",
        "entity_type_merged": "FAC",
        "has_name": true,
        "member_mention_ids": [
          "M049"
        ]
      },
      "E030": {
        "original_entity_id": "C30",
        "entity_type_merged": "FAC",
        "has_name": false,
        "member_mention_ids": [
          "M042"
        ]
      },
      "E031": {
        "original_entity_id": "C31",
        "entity_type_merged": "LINE",
        "has_name": false,
        "member_mention_ids": [
          "M044"
        ]
      },
      "E032": {
        "original_entity_id": "C32",
        "entity_type_merged": "LOC",
        "has_name": true,
        "member_mention_ids": [
          "M017"
        ]
      }
    }
  }
}