{
  "28749": {
    "sections": {
      "001": {
        "sentence_ids": [
          "001-01",
          "001-02"
        ]
      },
      "002": {
        "sentence_ids": [
          "002-01",
          "002-02"
        ]
      },
      "003": {
        "sentence_ids": [
          "003"
        ]
      },
      "004": {
        "sentence_ids": [
          "004-01",
          "004-02"
        ]
      },
      "005": {
        "sentence_ids": [
          "005"
        ]
      },
      "006": {
        "sentence_ids": [
          "006"
        ]
      },
      "007": {
        "sentence_ids": [
          "007-01",
          "007-02"
        ]
      },
      "008": {
        "sentence_ids": [
          "008"
        ]
      },
      "009": {
        "sentence_ids": [
          "009"
        ]
      },
      "010": {
        "sentence_ids": [
          "010"
        ]
      },
      "011": {
        "sentence_ids": [
          "011"
        ]
      },
      "012": {
        "sentence_ids": [
          "012-01",
          "012-02"
        ]
      },
      "013": {
        "sentence_ids": [
          "013-01",
          "013-02"
        ]
      },
      "014": {
        "sentence_ids": [
          "014"
        ]
      },
      "015": {
        "sentence_ids": [
          "015"
        ]
      },
      "016": {
        "sentence_ids": [
          "016"
        ]
      },
      "017": {
        "sentence_ids": [
          "017"
        ]
      },
      "018": {
        "sentence_ids": [
          "018"
        ]
      },
      "019": {
        "sentence_ids": [
          "019"
        ]
      },
      "020": {
        "sentence_ids": [
          "020"
        ]
      },
      "021": {
        "sentence_ids": [
          "021"
        ]
      },
      "022": {
        "sentence_ids": [
          "022"
        ]
      },
      "023": {
        "sentence_ids": [
          "023"
        ]
      },
      "024": {
        "sentence_ids": [
          "024"
        ]
      },
      "025": {
        "sentence_ids": [
          "025"
        ]
      },
      "026": {
        "sentence_ids": [
          "026-01",
          "026-02"
        ]
      },
      "027": {
        "sentence_ids": [
          "027"
        ]
      },
      "028": {
        "sentence_ids": [
          "028"
        ]
      },
      "029": {
        "sentence_ids": [
          "029"
        ]
      },
      "030": {
        "sentence_ids": [
          "030"
        ]
      },
      "031": {
        "sentence_ids": [
          "031"
        ]
      },
      "032": {
        "sentence_ids": [
          "032"
        ]
      },
      "033": {
        "sentence_ids": [
          "033"
        ]
      },
      "034": {
        "sentence_ids": [
          "034-01",
          "034-02",
          "034-03"
        ]
      },
      "035": {
        "sentence_ids": [
          "035"
        ]
      },
      "036": {
        "sentence_ids": [
          "036"
        ]
      },
      "037": {
        "sentence_ids": [
          "037-01",
          "037-02"
        ]
      },
      "038": {
        "sentence_ids": [
          "038-01",
          "038-02"
        ]
      },
      "039": {
        "sentence_ids": [
          "039-01",
          "039-02"
        ]
      },
      "040": {
        "sentence_ids": [
          "040"
        ]
      },
      "041": {
        "sentence_ids": [
          "041-01",
          "041-02"
        ]
      },
      "042": {
        "sentence_ids": [
          "042-01",
          "042-02",
          "042-03",
          "042-04",
          "042-05"
        ]
      }
    },
    "sentences": {
      "001-01": {
        "section_id": "001",
        "span_in_orig_text": [
          0,
          72
        ],
        "text": "",
        "mention_ids": [
          "M001",
          "M065",
          "M067",
          "M068"
        ]
      },
      "001-02": {
        "section_id": "001",
        "span_in_orig_text": [
          72,
          92
        ],
        "text": "",
        "mention_ids": [
          "M002",
          "M066"
        ]
      },
      "002-01": {
        "section_id": "002",
        "span_in_orig_text": [
          0,
          50
        ],
        "text": "",
        "mention_ids": [
          "M003",
          "M004",
          "M005",
          "M040"
        ]
      },
      "002-02": {
        "section_id": "002",
        "span_in_orig_text": [
          50,
          65
        ],
        "text": "",
        "mention_ids": [
          "M006"
        ]
      },
      "003": {
        "section_id": "003",
        "text": "",
        "mention_ids": [
          "M007",
          "M041",
          "M042"
        ]
      },
      "004-01": {
        "section_id": "004",
        "span_in_orig_text": [
          0,
          14
        ],
        "text": "",
        "mention_ids": [
          "M008"
        ]
      },
      "004-02": {
        "section_id": "004",
        "span_in_orig_text": [
          14,
          42
        ],
        "text": "",
        "mention_ids": [
          "M009",
          "M044",
          "M064"
        ]
      },
      "005": {
        "section_id": "005",
        "text": "",
        "mention_ids": [
          "M010",
          "M011",
          "M043"
        ]
      },
      "006": {
        "section_id": "006",
        "text": "",
        "mention_ids": [
          "M012",
          "M069"
        ]
      },
      "007-01": {
        "section_id": "007",
        "span_in_orig_text": [
          0,
          14
        ],
        "text": "",
        "mention_ids": [
          "M045"
        ]
      },
      "007-02": {
        "section_id": "007",
        "span_in_orig_text": [
          14,
          20
        ],
        "text": "",
        "mention_ids": [
          "M046"
        ]
      },
      "008": {
        "section_id": "008",
        "text": "",
        "mention_ids": [
          "M047"
        ]
      },
      "009": {
        "section_id": "009",
        "text": "",
        "mention_ids": [
          "M048"
        ]
      },
      "010": {
        "section_id": "010",
        "text": "",
        "mention_ids": [
          "M013",
          "M049"
        ]
      },
      "011": {
        "section_id": "011",
        "text": "",
        "mention_ids": [
          "M014",
          "M050"
        ]
      },
      "012-01": {
        "section_id": "012",
        "span_in_orig_text": [
          0,
          25
        ],
        "text": "",
        "mention_ids": [
          "M015"
        ]
      },
      "012-02": {
        "section_id": "012",
        "span_in_orig_text": [
          25,
          32
        ],
        "text": "",
        "mention_ids": []
      },
      "013-01": {
        "section_id": "013",
        "span_in_orig_text": [
          0,
          11
        ],
        "text": "",
        "mention_ids": [
          "M016"
        ]
      },
      "013-02": {
        "section_id": "013",
        "span_in_orig_text": [
          11,
          24
        ],
        "text": "",
        "mention_ids": [
          "M051"
        ]
      },
      "014": {
        "section_id": "014",
        "text": "",
        "mention_ids": [
          "M017"
        ]
      },
      "015": {
        "section_id": "015",
        "text": "",
        "mention_ids": [
          "M018"
        ]
      },
      "016": {
        "section_id": "016",
        "text": "",
        "mention_ids": []
      },
      "017": {
        "section_id": "017",
        "text": "",
        "mention_ids": []
      },
      "018": {
        "section_id": "018",
        "text": "",
        "mention_ids": []
      },
      "019": {
        "section_id": "019",
        "text": "",
        "mention_ids": [
          "M019",
          "M052"
        ]
      },
      "020": {
        "section_id": "020",
        "text": "",
        "mention_ids": [
          "M020"
        ]
      },
      "021": {
        "section_id": "021",
        "text": "",
        "mention_ids": []
      },
      "022": {
        "section_id": "022",
        "text": "",
        "mention_ids": [
          "M053"
        ]
      },
      "023": {
        "section_id": "023",
        "text": "",
        "mention_ids": [
          "M021"
        ]
      },
      "024": {
        "section_id": "024",
        "text": "",
        "mention_ids": [
          "M022"
        ]
      },
      "025": {
        "section_id": "025",
        "text": "",
        "mention_ids": []
      },
      "026-01": {
        "section_id": "026",
        "span_in_orig_text": [
          0,
          11
        ],
        "text": "",
        "mention_ids": [
          "M023"
        ]
      },
      "026-02": {
        "section_id": "026",
        "span_in_orig_text": [
          11,
          24
        ],
        "text": "",
        "mention_ids": [
          "M024"
        ]
      },
      "027": {
        "section_id": "027",
        "text": "",
        "mention_ids": [
          "M025",
          "M026"
        ]
      },
      "028": {
        "section_id": "028",
        "text": "",
        "mention_ids": [
          "M054",
          "M070"
        ]
      },
      "029": {
        "section_id": "029",
        "text": "",
        "mention_ids": [
          "M056"
        ]
      },
      "030": {
        "section_id": "030",
        "text": "",
        "mention_ids": [
          "M055"
        ]
      },
      "031": {
        "section_id": "031",
        "text": "",
        "mention_ids": [
          "M027",
          "M028"
        ]
      },
      "032": {
        "section_id": "032",
        "text": "",
        "mention_ids": [
          "M057"
        ]
      },
      "033": {
        "section_id": "033",
        "text": "",
        "mention_ids": []
      },
      "034-01": {
        "section_id": "034",
        "span_in_orig_text": [
          0,
          8
        ],
        "text": "",
        "mention_ids": []
      },
      "034-02": {
        "section_id": "034",
        "span_in_orig_text": [
          8,
          19
        ],
        "text": "",
        "mention_ids": []
      },
      "034-03": {
        "section_id": "034",
        "span_in_orig_text": [
          19,
          33
        ],
        "text": "",
        "mention_ids": [
          "M029"
        ]
      },
      "035": {
        "section_id": "035",
        "text": "",
        "mention_ids": [
          "M030",
          "M058"
        ]
      },
      "036": {
        "section_id": "036",
        "text": "",
        "mention_ids": [
          "M059"
        ]
      },
      "037-01": {
        "section_id": "037",
        "span_in_orig_text": [
          0,
          41
        ],
        "text": "",
        "mention_ids": [
          "M031",
          "M060"
        ]
      },
      "037-02": {
        "section_id": "037",
        "span_in_orig_text": [
          41,
          67
        ],
        "text": "",
        "mention_ids": [
          "M032"
        ]
      },
      "038-01": {
        "section_id": "038",
        "span_in_orig_text": [
          0,
          8
        ],
        "text": "",
        "mention_ids": [
          "M033"
        ]
      },
      "038-02": {
        "section_id": "038",
        "span_in_orig_text": [
          8,
          22
        ],
        "text": "",
        "mention_ids": []
      },
      "039-01": {
        "section_id": "039",
        "span_in_orig_text": [
          0,
          17
        ],
        "text": "",
        "mention_ids": [
          "M061"
        ]
      },
      "039-02": {
        "section_id": "039",
        "span_in_orig_text": [
          17,
          29
        ],
        "text": "",
        "mention_ids": []
      },
      "040": {
        "section_id": "040",
        "text": "",
        "mention_ids": [
          "M034",
          "M035"
        ]
      },
      "041-01": {
        "section_id": "041",
        "span_in_orig_text": [
          0,
          14
        ],
        "text": "",
        "mention_ids": []
      },
      "041-02": {
        "section_id": "041",
        "span_in_orig_text": [
          14,
          34
        ],
        "text": "",
        "mention_ids": [
          "M062",
          "M071"
        ]
      },
      "042-01": {
        "section_id": "042",
        "span_in_orig_text": [
          0,
          13
        ],
        "text": "",
        "mention_ids": [
          "M036"
        ]
      },
      "042-02": {
        "section_id": "042",
        "span_in_orig_text": [
          13,
          58
        ],
        "text": "",
        "mention_ids": [
          "M037",
          "M038",
          "M063"
        ]
      },
      "042-03": {
        "section_id": "042",
        "span_in_orig_text": [
          58,
          94
        ],
        "text": "",
        "mention_ids": [
          "M039"
        ]
      },
      "042-04": {
        "section_id": "042",
        "span_in_orig_text": [
          94,
          116
        ],
        "text": "",
        "mention_ids": []
      },
      "042-05": {
        "section_id": "042",
        "span_in_orig_text": [
          116,
          121
        ],
        "text": "",
        "mention_ids": []
      }
    },
    "mentions": {
      "M067": {
        "sentence_id": "001-01",
        "entity_id": null,
        "span": [
          0,
          3
        ],
        "text": "",
        "entity_type": "TRANS_NAME"
      },
      "M068": {
        "sentence_id": "001-01",
        "entity_id": null,
        "span": [
          4,
          7
        ],
        "text": "",
        "entity_type": "TRANS_NAME"
      },
      "M065": {
        "sentence_id": "001-01",
        "entity_id": "E001",
        "span": [
          25,
          27
        ],
        "text": "",
        "entity_type": "DEICTIC"
      },
      "M001": {
        "sentence_id": "001-01",
        "entity_id": "E002",
        "span": [
          44,
          50
        ],
        "text": "",
        "entity_type": "LOC_NAME"
      },
      "M066": {
        "sentence_id": "001-02",
        "entity_id": null,
        "span": [
          0,
          3
        ],
        "text": "",
        "entity_type": "TRANS_NAME"
      },
      "M002": {
        "sentence_id": "001-02",
        "entity_id": "E003",
        "span": [
          8,
          12
        ],
        "text": "",
        "entity_type": "FAC_NAME"
      },
      "M003": {
        "sentence_id": "002-01",
        "entity_id": "E003",
        "span": [
          0,
          4
        ],
        "text": "",
        "entity_type": "FAC_NAME"
      },
      "M040": {
        "sentence_id": "002-01",
        "entity_id": null,
        "span": [
          8,
          14
        ],
        "text": "",
        "entity_type": "TRANS_NAME"
      },
      "M004": {
        "sentence_id": "002-01",
        "entity_id": "E004",
        "span": [
          15,
          22
        ],
        "text": "",
        "entity_type": "FAC_NAME"
      },
      "M005": {
        "sentence_id": "002-01",
        "entity_id": "E005",
        "span": [
          33,
          36
        ],
        "text": "",
        "entity_type": "FAC_NAME"
      },
      "M006": {
        "sentence_id": "002-02",
        "entity_id": "E005",
        "span": [
          0,
          3
        ],
        "text": "",
        "entity_type": "FAC_NAME"
      },
      "M041": {
        "sentence_id": "003",
        "entity_id": null,
        "span": [
          0,
          2
        ],
        "text": "",
        "entity_type": "TRANS_NOM"
      },
      "M007": {
        "sentence_id": "003",
        "entity_id": "E006",
        "span": [
          3,
          5
        ],
        "text": "",
        "entity_type": "LOC_NAME"
      },
      "M042": {
        "sentence_id": "003",
        "entity_id": "E007",
        "span": [
          6,
          9
        ],
        "text": "",
        "entity_type": "LOC_NOM"
      },
      "M008": {
        "sentence_id": "004-01",
        "entity_id": "E004",
        "span": [
          0,
          7
        ],
        "text": "",
        "entity_type": "FAC_NAME"
      },
      "M064": {
        "sentence_id": "004-02",
        "entity_id": "E004",
        "span": [
          0,
          2
        ],
        "text": "",
        "entity_type": "DEICTIC"
      },
      "M044": {
        "sentence_id": "004-02",
        "entity_id": "E008",
        "span": [
          12,
          13
        ],
        "text": "",
        "entity_type": "FAC_NOM"
      },
      "M009": {
        "sentence_id": "004-02",
        "entity_id": "E008",
        "span": [
          14,
          21
        ],
        "text": "",
        "entity_type": "FAC_NAME"
      },
      "M043": {
        "sentence_id": "005",
        "entity_id": "E009",
        "span": [
          0,
          3
        ],
        "text": "",
        "entity_type": "FAC_NOM"
      },
      "M010": {
        "sentence_id": "005",
        "entity_id": "E010",
        "span": [
          4,
          7
        ],
        "text": "",
        "entity_type": "LOC_NAME"
      },
      "M011": {
        "sentence_id": "005",
        "entity_id": "E002",
        "span": [
          17,
          23
        ],
        "text": "",
        "entity_type": "LOC_NAME"
      },
      "M069": {
        "sentence_id": "006",
        "entity_id": "E010",
        "span": [
          0,
          2
        ],
        "text": "",
        "entity_type": "DEICTIC"
      },
      "M012": {
        "sentence_id": "006",
        "entity_id": "E011",
        "span": [
          5,
          13
        ],
        "text": "",
        "entity_type": "LINE_NAME"
      },
      "M045": {
        "sentence_id": "007-01",
        "entity_id": null,
        "span": [
          3,
          5
        ],
        "text": "",
        "entity_type": "LOC_NOM",
        "ref_spec_amb": true
      },
      "M046": {
        "sentence_id": "007-02",
        "entity_id": null,
        "span": [
          0,
          3
        ],
        "text": "",
        "entity_type": "LOC_NOM",
        "ref_spec_amb": true
      },
      "M047": {
        "sentence_id": "008",
        "entity_id": null,
        "span": [
          10,
          12
        ],
        "text": "",
        "entity_type": "LOC_NOM",
        "ref_spec_amb": true
      },
      "M048": {
        "sentence_id": "009",
        "entity_id": "E012",
        "span": [
          0,
          3
        ],
        "text": "",
        "entity_type": "LOC_NAME"
      },
      "M049": {
        "sentence_id": "010",
        "entity_id": "E013",
        "span": [
          0,
          4
        ],
        "text": "",
        "entity_type": "LOC_NAME"
      },
      "M013": {
        "sentence_id": "010",
        "entity_id": "E002",
        "span": [
          9,
          15
        ],
        "text": "",
        "entity_type": "LOC_NAME"
      },
      "M050": {
        "sentence_id": "011",
        "entity_id": "E014",
        "span": [
          3,
          4
        ],
        "text": "",
        "entity_type": "LOC_NOM"
      },
      "M014": {
        "sentence_id": "011",
        "entity_id": "E014",
        "span": [
          5,
          8
        ],
        "text": "",
        "entity_type": "LOC_NAME"
      },
      "M015": {
        "sentence_id": "012-01",
        "entity_id": "E015",
        "span": [
          11,
          18
        ],
        "text": "",
        "entity_type": "FAC_NAME"
      },
      "M016": {
        "sentence_id": "013-01",
        "entity_id": "E015",
        "span": [
          3,
          10
        ],
        "text": "",
        "entity_type": "FAC_NAME"
      },
      "M051": {
        "sentence_id": "013-02",
        "entity_id": null,
        "span": [
          0,
          1
        ],
        "text": "",
        "entity_type": "LOC_NOM",
        "ref_spec_amb": true
      },
      "M017": {
        "sentence_id": "014",
        "entity_id": "E016",
        "span": [
          0,
          2
        ],
        "text": "",
        "entity_type": "LOC_NAME"
      },
      "M018": {
        "sentence_id": "015",
        "entity_id": "E017",
        "span": [
          6,
          10
        ],
        "text": "",
        "entity_type": "LOC_NAME"
      },
      "M019": {
        "sentence_id": "019",
        "entity_id": "E018",
        "span": [
          0,
          4
        ],
        "text": "",
        "entity_type": "LOC_NAME"
      },
      "M052": {
        "sentence_id": "019",
        "entity_id": "E019",
        "span": [
          6,
          10
        ],
        "text": "",
        "entity_type": "FAC_NOM"
      },
      "M020": {
        "sentence_id": "020",
        "entity_id": "E016",
        "span": [
          7,
          9
        ],
        "text": "",
        "entity_type": "LOC_NAME"
      },
      "M053": {
        "sentence_id": "022",
        "entity_id": "E016",
        "span": [
          2,
          3
        ],
        "text": "",
        "entity_type": "LOC_NOM"
      },
      "M021": {
        "sentence_id": "023",
        "entity_id": "E020",
        "span": [
          0,
          3
        ],
        "text": "",
        "entity_type": "LOC_NAME"
      },
      "M022": {
        "sentence_id": "024",
        "entity_id": "E021",
        "span": [
          0,
          2
        ],
        "text": "",
        "entity_type": "LOC_NAME"
      },
      "M023": {
        "sentence_id": "026-01",
        "entity_id": "E022",
        "span": [
          0,
          4
        ],
        "text": "",
        "entity_type": "LOC_NAME"
      },
      "M024": {
        "sentence_id": "026-02",
        "entity_id": "E002",
        "span": [
          0,
          6
        ],
        "text": "",
        "entity_type": "LOC_NAME"
      },
      "M025": {
        "sentence_id": "027",
        "entity_id": "E022",
        "span": [
          0,
          4
        ],
        "text": "",
        "entity_type": "LOC_NAME"
      },
      "M026": {
        "sentence_id": "027",
        "entity_id": "E021",
        "span": [
          7,
          9
        ],
        "text": "",
        "entity_type": "LOC_NAME"
      },
      "M070": {
        "sentence_id": "028",
        "entity_id": "E023",
        "span": [
          0,
          2
        ],
        "text": "",
        "entity_type": "DEICTIC"
      },
      "M054": {
        "sentence_id": "028",
        "entity_id": null,
        "span": [
          3,
          4
        ],
        "text": "",
        "entity_type": "LOC_NOM",
        "generic": true
      },
      "M056": {
        "sentence_id": "029",
        "entity_id": "E024",
        "span": [
          0,
          3
        ],
        "text": "",
        "entity_type": "FAC_NAME"
      },
      "M055": {
        "sentence_id": "030",
        "entity_id": "E021",
        "span": [
          0,
          2
        ],
        "text": "",
        "entity_type": "LOC_NAME"
      },
      "M027": {
        "sentence_id": "031",
        "entity_id": "E016",
        "span": [
          0,
          2
        ],
        "text": "",
        "entity_type": "LOC_NAME"
      },
      "M028": {
        "sentence_id": "031",
        "entity_id": "E020",
        "span": [
          6,
          9
        ],
        "text": "",
        "entity_type": "LOC_NAME"
      },
      "M057": {
        "sentence_id": "032",
        "entity_id": null,
        "span": [
          4,
          5
        ],
        "text": "",
        "entity_type": "LOC_NOM",
        "ref_spec_amb": true
      },
      "M029": {
        "sentence_id": "034-03",
        "entity_id": "E025",
        "span": [
          0,
          3
        ],
        "text": "",
        "entity_type": "LOC_NAME"
      },
      "M030": {
        "sentence_id": "035",
        "entity_id": "E025",
        "span": [
          7,
          10
        ],
        "text": "",
        "entity_type": "LOC_NAME"
      },
      "M058": {
        "sentence_id": "035",
        "entity_id": null,
        "span": [
          17,
          19
        ],
        "text": "",
        "entity_type": "LOC_NOM",
        "ref_spec_amb": true
      },
      "M059": {
        "sentence_id": "036",
        "entity_id": null,
        "span": [
          2,
          4
        ],
        "text": "",
        "entity_type": "LOC_NOM",
        "ref_spec_amb": true
      },
      "M031": {
        "sentence_id": "037-01",
        "entity_id": "E026",
        "span": [
          0,
          3
        ],
        "text": "",
        "entity_type": "LOC_NAME",
        "ref_hie_amb": true
      },
      "M060": {
        "sentence_id": "037-01",
        "entity_id": null,
        "span": [
          5,
          7
        ],
        "text": "",
        "entity_type": "TRANS_NOM"
      },
      "M032": {
        "sentence_id": "037-02",
        "entity_id": "E027",
        "span": [
          9,
          12
        ],
        "text": "",
        "entity_type": "LOC_NAME"
      },
      "M033": {
        "sentence_id": "038-01",
        "entity_id": "E027",
        "span": [
          0,
          3
        ],
        "text": "",
        "entity_type": "LOC_NAME"
      },
      "M061": {
        "sentence_id": "039-01",
        "entity_id": "E028",
        "span": [
          12,
          14
        ],
        "text": "",
        "entity_type": "FAC_NOM"
      },
      "M034": {
        "sentence_id": "040",
        "entity_id": "E026",
        "span": [
          0,
          3
        ],
        "text": "",
        "entity_type": "LOC_NAME",
        "ref_hie_amb": true
      },
      "M035": {
        "sentence_id": "040",
        "entity_id": "E029",
        "span": [
          5,
          7
        ],
        "text": "",
        "entity_type": "LOC_NAME",
        "ref_hie_amb": true
      },
      "M071": {
        "sentence_id": "041-02",
        "entity_id": "E030",
        "span": [
          3,
          4
        ],
        "text": "",
        "entity_type": "FAC_NOM"
      },
      "M062": {
        "sentence_id": "041-02",
        "entity_id": "E031",
        "span": [
          6,
          11
        ],
        "text": "",
        "entity_type": "FAC_NOM"
      },
      "M036": {
        "sentence_id": "042-01",
        "entity_id": "E029",
        "span": [
          3,
          5
        ],
        "text": "",
        "entity_type": "LOC_NAME",
        "ref_hie_amb": true
      },
      "M063": {
        "sentence_id": "042-02",
        "entity_id": null,
        "span": [
          0,
          2
        ],
        "text": "",
        "entity_type": "FAC_NOM",
        "ref_spec_amb": true
      },
      "M037": {
        "sentence_id": "042-02",
        "entity_id": "E032",
        "span": [
          23,
          27
        ],
        "text": "",
        "entity_type": "FAC_NAME"
      },
      "M038": {
        "sentence_id": "042-02",
        "entity_id": "E033",
        "span": [
          36,
          38
        ],
        "text": "",
        "entity_type": "FAC_NOM"
      },
      "M039": {
        "sentence_id": "042-03",
        "entity_id": "E002",
        "span": [
          16,
          22
        ],
        "text": "",
        "entity_type": "LOC_NAME"
      }
    },
    "entities": {
      "E001": {
        "original_entity_id": "C1",
        "entity_type_merged": "UNK",
        "has_name": false,
        "has_reference": false,
        "member_mention_ids": [
          "M065"
        ]
      },
      "E002": {
        "original_entity_id": "C2",
        "entity_type_merged": "LOC",
        "has_name": true,
        "has_reference": false,
        "member_mention_ids": [
          "M001",
          "M011",
          "M013",
          "M024",
          "M039"
        ]
      },
      "E003": {
        "original_entity_id": "C3",
        "entity_type_merged": "FAC",
        "has_name": true,
        "has_reference": false,
        "member_mention_ids": [
          "M002",
          "M003"
        ]
      },
      "E004": {
        "original_entity_id": "C4",
        "entity_type_merged": "FAC",
        "has_name": true,
        "has_reference": false,
        "member_mention_ids": [
          "M004",
          "M008",
          "M064"
        ]
      },
      "E005": {
        "original_entity_id": "C5",
        "entity_type_merged": "FAC",
        "has_name": true,
        "has_reference": false,
        "member_mention_ids": [
          "M005",
          "M006"
        ]
      },
      "E006": {
        "original_entity_id": "C6",
        "entity_type_merged": "LOC",
        "has_name": true,
        "has_reference": false,
        "member_mention_ids": [
          "M007"
        ]
      },
      "E007": {
        "original_entity_id": "C7",
        "entity_type_merged": "LOC",
        "has_name": false,
        "has_reference": false,
        "member_mention_ids": [
          "M042"
        ]
      },
      "E008": {
        "original_entity_id": "C8",
        "entity_type_merged": "FAC",
        "has_name": true,
        "coref_attr_pairs": "T9-T44",
        "has_reference": false,
        "member_mention_ids": [
          "M009",
          "M044"
        ]
      },
      "E009": {
        "original_entity_id": "C9",
        "entity_type_merged": "FAC",
        "has_name": false,
        "has_reference": false,
        "member_mention_ids": [
          "M043"
        ]
      },
      "E010": {
        "original_entity_id": "C10",
        "entity_type_merged": "LOC",
        "has_name": true,
        "has_reference": false,
        "member_mention_ids": [
          "M010",
          "M069"
        ]
      },
      "E011": {
        "original_entity_id": "C11",
        "entity_type_merged": "LINE",
        "has_name": true,
        "has_reference": false,
        "member_mention_ids": [
          "M012"
        ]
      },
      "E012": {
        "original_entity_id": "C12",
        "entity_type_merged": "LOC",
        "has_name": true,
        "has_reference": false,
        "member_mention_ids": [
          "M048"
        ]
      },
      "E013": {
        "original_entity_id": "C13",
        "entity_type_merged": "LOC",
        "has_name": true,
        "has_reference": false,
        "member_mention_ids": [
          "M049"
        ]
      },
      "E014": {
        "original_entity_id": "C14",
        "entity_type_merged": "LOC",
        "has_name": true,
        "coref_attr_pairs": "T14-T50",
        "has_reference": false,
        "member_mention_ids": [
          "M014",
          "M050"
        ]
      },
      "E015": {
        "original_entity_id": "C15",
        "entity_type_merged": "FAC",
        "has_name": true,
        "has_reference": false,
        "member_mention_ids": [
          "M015",
          "M016"
        ]
      },
      "E016": {
        "original_entity_id": "C16",
        "entity_type_merged": "LOC",
        "has_name": true,
        "has_reference": false,
        "member_mention_ids": [
          "M017",
          "M020",
          "M027",
          "M053"
        ]
      },
      "E017": {
        "original_entity_id": "C17",
        "entity_type_merged": "LOC",
        "has_name": true,
        "has_reference": false,
        "member_mention_ids": [
          "M018"
        ]
      },
      "E018": {
        "original_entity_id": "C18",
        "entity_type_merged": "LOC",
        "has_name": true,
        "has_reference": false,
        "member_mention_ids": [
          "M019"
        ]
      },
      "E019": {
        "original_entity_id": "C19",
        "entity_type_merged": "FAC",
        "has_name": false,
        "has_reference": false,
        "member_mention_ids": [
          "M052"
        ]
      },
      "E020": {
        "original_entity_id": "C20",
        "entity_type_merged": "LOC",
        "has_name": true,
        "has_reference": false,
        "member_mention_ids": [
          "M021",
          "M028"
        ]
      },
      "E021": {
        "original_entity_id": "C21",
        "entity_type_merged": "LOC",
        "has_name": true,
        "has_reference": false,
        "member_mention_ids": [
          "M022",
          "M026",
          "M055"
        ]
      },
      "E022": {
        "original_entity_id": "C22",
        "entity_type_merged": "LOC",
        "has_name": true,
        "has_reference": false,
        "member_mention_ids": [
          "M023",
          "M025"
        ]
      },
      "E023": {
        "original_entity_id": "C23",
        "entity_type_merged": "UNK",
        "has_name": false,
        "has_reference": false,
        "member_mention_ids": [
          "M070"
        ]
      },
      "E024": {
        "original_entity_id": "C24",
        "entity_type_merged": "FAC",
        "has_name": true,
        "has_reference": false,
        "member_mention_ids": [
          "M056"
        ]
      },
      "E025": {
        "original_entity_id": "C25",
        "entity_type_merged": "LOC",
        "has_name": true,
        "has_reference": false,
        "member_mention_ids": [
          "M029",
          "M030"
        ]
      },
      "E026": {
        "original_entity_id": "C26",
        "entity_type_merged": "LOC",
        "has_name": true,
        "has_reference": false,
        "member_mention_ids": [
          "M031",
          "M034"
        ]
      },
      "E027": {
        "original_entity_id": "C27",
        "entity_type_merged": "LOC",
        "has_name": true,
        "has_reference": false,
        "member_mention_ids": [
          "M032",
          "M033"
        ]
      },
      "E028": {
        "original_entity_id": "C28",
        "entity_type_merged": "FAC",
        "has_name": false,
        "has_reference": false,
        "member_mention_ids": [
          "M061"
        ]
      },
      "E029": {
        "original_entity_id": "C29",
        "entity_type_merged": "LOC",
        "has_name": true,
        "has_reference": false,
        "member_mention_ids": [
          "M035",
          "M036"
        ]
      },
      "E030": {
        "original_entity_id": "C30",
        "entity_type_merged": "FAC",
        "has_name": false,
        "has_reference": false,
        "member_mention_ids": [
          "M071"
        ]
      },
      "E031": {
        "original_entity_id": "C31",
        "entity_type_merged": "FAC",
        "has_name": false,
        "has_reference": false,
        "member_mention_ids": [
          "M062"
        ]
      },
      "E032": {
        "original_entity_id": "C32",
        "entity_type_merged": "FAC",
        "has_name": true,
        "has_reference": false,
        "member_mention_ids": [
          "M037"
        ]
      },
      "E033": {
        "original_entity_id": "C33",
        "entity_type_merged": "FAC",
        "has_name": false,
        "has_reference": false,
        "member_mention_ids": [
          "M038"
        ]
      }
    }
  }
}